{
    "snippets.snipmate.author": "Yue Peng",
    "snippets.snipmate.enable": false,
    "snippets.shortcut": "S",
    "snippets.priority": 98,
    "snippets.extends": {
        "cpp": ["c"],
        "javascriptreact": ["javascript"],
        "typescript": ["javascript"]
    },
    "coc.source.file.shortcut": "F",
    "coc.source.file.priority": 89,
    "coc.source.file.ignoreHidden": false,
    "coc.source.around.shortcut": "A",
    "coc.source.around.priority": 88,
    "coc.source.buffer.shortcut": "B",
    "coc.source.buffer.priority": 87,
    "coc.source.buffer.ignoreGitignore": false,
    "coc.source.syntax.shortcut": "X",
    "coc.source.syntax.priority": 79,
    "coc.source.tag.shortcut": "T",
    "coc.source.tag.priority": 78,
    "coc.source.dictionary.shortcut": "D",
    "coc.source.dictionary.priority": 9,
    "coc.source.dictionary.filetypes": ["markdown", "text"],
    "coc.source.emoji.shortcut": "E",
    "coc.source.emoji.priority": 8,
    "coc.source.emoji.filetypes": ["markdown", "text"],
    "highlight.document.enable": true,
    "highlight.colors.enable": false,
    "highlight.disableLanguages": [],
    // suggest
    "suggest.triggerAfterInsertEnter": false,
    "suggest.timeout": 5000,
    "suggest.noselect": false,
    "suggest.detailField":"preview",
    "suggest.snippetIndicator": "🌟",
    "suggest.triggerCompletionWait": 100,
    "suggest.echodocSupport": true,
    "suggest.completionItemKindLabels": {
        "keyword": "\uf1de",
        "variable": "\ue79b",
        "value": "\uf89f",
        "operator": "\u03a8",
        "function": "\u2A15",
        "reference": "\ufa46",
        "constant": "\uf8fe",
        "method": "\uf09a",
        "struct": "\ufb44",
        "class": "\uf0e8",
        "interface": "\uf417",
        "text": "\u2663",
        "enum": "\uf435",
        "enumMember": "\uf02b",
        "module": "\uf530",
        "color": "\ue22b",
        "property": "\ue624",
        "field": "\uf6a6",
        "unit": "\uf475",
        "event": "\ufacd",
        "file": "\uf723",
        "folder": "\uf114",
        "snippet": "\ue60b",
        "typeParameter": "\uf728",
        "default": "\uf29c"
    },
    //diagnostic
    "diagnostic.signOffset": 9999999,
    "diagnostic.errorSign": "✘",
	"diagnostic.warningSign": "✎",
    "diagnostic.displayByAle": false,
    "diagnostic.refreshOnInsertMode": true,
    //git
    "git.enableGutters": true,
    "git.branchCharacter":"\uf408",
    "git.addGBlameToBufferVar": true,
    "git.addGBlameToVirtualText": true,
    "git.virtualTextPrefix": " ❯❯❯ ",
    "git.addedSign.hlGroup": "GitGutterAdd",
    "git.changedSign.hlGroup": "GitGutterChange",
    "git.removedSign.hlGroup": "GitGutterDelete",
    "git.topRemovedSign.hlGroup": "GitGutterDelete",
    "git.changeRemovedSign.hlGroup": "GitGutterChangeDelete",
    "git.addedSign.text":"▎",
    "git.changedSign.text":"▎",
    "git.removedSign.text":"▏",
    "git.topRemovedSign.text": "▔",
    "git.changeRemovedSign.text": "▋",
    //Snippet
    "coc.preferences.snippetStatusText": "Ⓢ ",
    //tslint
    //"tslint.autoFixOnSave": true,
    "coc.preferences.formatOnSaveFiletypes": ["css","markdown"],
    //python
    "python.autoComplete.addBrackets": true,
    "python.jediEnabled": true,
    "python.jediPath": "/usr/local/lib/python3.8/site-packages",
    "python.linting.flake8Enabled": true,
	"python.linting.flake8Path": "/usr/local/bin/flake8",
    "python.linting.pydocstyleEnabled": true,
    "python.linting.pydocstylePath": "/usr/local/bin/pycodestyle",
	"python.formatting.provider": "black",
    "python.formatting.blackPath": "/usr/local/bin/black",
    // pairs
    "pairs.enableBackspace": false,
    "pairs.enableCharacters": ["(", "[", "{", "'", "\"", "`"],
    // ls
    "languageserver": {
        // "MPLS": {
        //     "command": "mspyls",
        //     "trace.server": "verbose",
        //     "filetypes": ["none"],
        //     "filetypes_bak": ["python"],
        //     "initializationOptions": {
        //         "interpreter": {
        //         "properties": {
        //             "InterpreterPath": "/usr/bin/python3",
        //             "UseDefaultDatabase": true
        //         }
        //         },
        //         "displayOptions": {
        //         "preferredFormat": "markdown",
        //         "trimDocumentationLines": false,
        //         "maxDocumentationLineLength": 0,
        //         "trimDocumentationText": false,
        //         "maxDocumentationTextLength": 0
        //         },
        //         "searchPaths": ["/usr/bin"],
        //         "testEnvironment": false,
        //         "analysisUpdates": true,
        //         "traceLogging": true,
        //         "asyncStartup": true
        //     }
        // },
        // "python": {
        //     "command": "pyls",
        //     "args": [],
        //     "filetypes": ["python", "py"]
        // },
        "golang": {
            "command": "gopls",
            "args": [],
            "disableWorkspaceFolders": true,
            "rootPatterns": ["go.mod", ".vim/", ".git/", ".hg/"],
            "filetypes": ["go"]
        },
        // "rust": {
        //     "command": "ra_lsp_server",
        //     "filetypes": ["rust"],
        //     "rootPatterns": ["Cargo.toml"]
        // },
        "bash": {
            "command": "bash-language-server",
            "args": ["start"],
            "filetypes": ["sh"],
            "ignoredRootPaths": ["~"]
        },
        "dockerfile": {
            "command": "docker-langserver",
            "filetypes": ["dockerfile"],
            "args": ["--stdio"]
        }
        // "ccls": {
        //     "command": "ccls",
        //     "filetypes": ["c", "cpp", "objc", "objcpp"],
        //     "rootPatterns": [".ccls", "compile_commands.json", ".vim/", ".git/", ".hg/"],
        //     "initializationOptions": {
        //         "cache": {
        //             "directory": "/tmp/ccls",
        //             "format": "json"
        //         },
        //         "clang": {
        //         // make sure you have installed commandLineTools
        //         "resourceDir": "/Library/Developer/CommandLineTools/usr/lib/clang/10.0.1",
        //         "extraArgs": [
        //             "-isystem",
        //             "/Applications/Xcode.app/Contents/Developer/Toolchains/XcodeDefault.xctoolchain/usr/include/c++/",
        //             "-I",
        //             "/Applications/Xcode.app/Contents/Developer/Platforms/MacOSX.platform/Developer/SDKs/MacOSX.sdk/usr/include/"
        //             ]
        //         }
        //     }
        // }
    },
    // browser
    // "coc.browser.enable": true,
    // "coc.browser.shortcut": "web",
    // "coc.browser.capacity": 5,
    // "coc.browser.priority": 5,
    "clangd.path": "/Users/yuepeng/.config/coc/extensions/coc-clangd-data/install/10.0.0/clangd_10.0.0/bin/clangd"
}
